{"id": "movielen", "path": "c:\\Projects\\python\\recommender\\datasets\\movielen.py", "mtime": 1561168118, "size": 2823, "hash": "1089a0ca343c4a733282589cf2a976b8", "data_mtime": 1561168114, "dependencies": ["pathlib", "typing", "builtins", "abc"], "suppressed": ["numpy", "pandas", "tensorflow"], "child_modules": [], "options": {"mypyc": false, "disallow_any_generics": false, "plugins": [], "always_false": [], "disallow_untyped_defs": false, "always_true": [], "disallow_any_expr": false, "disallow_any_decorated": false, "strict_optional": true, "disallow_untyped_decorators": false, "disallow_incomplete_defs": false, "warn_unused_ignores": false, "no_implicit_optional": false, "warn_no_return": true, "follow_imports": "silent", "ignore_errors": false, "allow_redefinition": false, "disallow_subclassing_any": false, "local_partial_types": false, "implicit_reexport": true, "disallow_untyped_calls": false, "follow_imports_for_stubs": false, "platform": "win32", "warn_return_any": false, "strict_optional_whitelist": null, "disallow_any_unimported": false, "new_semantic_analyzer": false, "ignore_missing_imports": true, "bazel": false, "show_none_errors": true, "check_untyped_defs": false, "disallow_any_explicit": false, "strict_equality": false, "allow_untyped_globals": false}, "dep_prios": [5, 5, 5, 30, 10, 10, 5], "dep_lines": [1, 2, 1, 1, 4, 5, 6], "interface_hash": "0265c430c1dfd41584d3e36daf81e962", "version_id": "0.710", "ignore_all": false}